{"name": "Tall Kayf", "region": "Ninawa", "country": "Iraq", "lat": 36.53, "lon": 43.27, "sunrise": 290, "sunset": 1169, "weather": [{"hour": 0, "temp_c": 31.650000000000002, "is_day": 0.0, "wind_kph": 12.962499999999999, "pressure_mb": 1001.5, "precip_mm": 0.0, "humidity": 17.375, "cloud": 0.0, "feelslike_c": 29.4625, "will_it_rain": 0.0, "chance_of_rain": 0.0, "will_it_snow": 0.0, "chance_of_snow": 0.0, "vis_km": 10.0, "gust_kph": 26.775000000000002, "uv": 1.0}, {"hour": 1, "temp_c": 30.875, "is_day": 0.0, "wind_kph": 13.0375, "pressure_mb": 1001.125, "precip_mm": 0.0, "humidity": 18.625, "cloud": 0.25, "feelslike_c": 28.725, "will_it_rain": 0.0, "chance_of_rain": 0.0, "will_it_snow": 0.0, "chance_of_snow": 0.0, "vis_km": 10.0, "gust_kph": 26.862499999999997, "uv": 1.0}, {"hour": 2, "temp_c": 30.125, "is_day": 0.0, "wind_kph": 11.2125, "pressure_mb": 1001.25, "precip_mm": 0.0, "humidity": 20.125, "cloud": 0.25, "feelslike_c": 28.075, "will_it_rain": 0.0, "chance_of_rain": 0.0, "will_it_snow": 0.0, "chance_of_snow": 0.0, "vis_km": 10.0, "gust_kph": 23.225000000000005, "uv": 1.0}, {"hour": 3, "temp_c": 29.4, "is_day": 0.0, "wind_kph": 10.525000000000002, "pressure_mb": 1001.125, "precip_mm": 0.0, "humidity": 22.375, "cloud": 0.25, "feelslike_c": 27.562499999999993, "will_it_rain": 0.0, "chance_of_rain": 0.0, "will_it_snow": 0.0, "chance_of_snow": 0.0, "vis_km": 10.0, "gust_kph": 21.650000000000002, "uv": 1.0}, {"hour": 4, "temp_c": 28.75, "is_day": 0.0, "wind_kph": 9.7125, "pressure_mb": 1001.375, "precip_mm": 0.0, "humidity": 24.125, "cloud": 0.25, "feelslike_c": 27.1125, "will_it_rain": 0.0, "chance_of_rain": 0.0, "will_it_snow": 0.0, "chance_of_snow": 0.0, "vis_km": 10.0, "gust_kph": 20.0625, "uv": 1.0}, {"hour": 5, "temp_c": 28.462500000000002, "is_day": 1.0, "wind_kph": 8.55, "pressure_mb": 1001.375, "precip_mm": 0.0, "humidity": 25.375, "cloud": 0.25, "feelslike_c": 26.987499999999997, "will_it_rain": 0.0, "chance_of_rain": 0.0, "will_it_snow": 0.0, "chance_of_snow": 0.0, "vis_km": 10.0, "gust_kph": 17.587500000000002, "uv": 7.0}, {"hour": 6, "temp_c": 29.587500000000002, "is_day": 1.0, "wind_kph": 7.5125, "pressure_mb": 1001.625, "precip_mm": 0.0, "humidity": 25.25, "cloud": 0.25, "feelslike_c": 27.987499999999997, "will_it_rain": 0.0, "chance_of_rain": 0.0, "will_it_snow": 0.0, "chance_of_snow": 0.0, "vis_km": 10.0, "gust_kph": 13.325, "uv": 7.375}, {"hour": 7, "temp_c": 31.4, "is_day": 1.0, "wind_kph": 8.225, "pressure_mb": 1002.0, "precip_mm": 0.0, "humidity": 22.625, "cloud": 0.25, "feelslike_c": 29.5375, "will_it_rain": 0.0, "chance_of_rain": 0.0, "will_it_snow": 0.0, "chance_of_snow": 0.0, "vis_km": 10.0, "gust_kph": 10.525, "uv": 8.0}, {"hour": 8, "temp_c": 33.1375, "is_day": 1.0, "wind_kph": 8.325, "pressure_mb": 1002.125, "precip_mm": 0.0, "humidity": 20.5, "cloud": 0.25, "feelslike_c": 31.237500000000004, "will_it_rain": 0.0, "chance_of_rain": 0.0, "will_it_snow": 0.0, "chance_of_snow": 0.0, "vis_km": 10.0, "gust_kph": 9.6375, "uv": 8.0}, {"hour": 9, "temp_c": 34.85, "is_day": 1.0, "wind_kph": 8.225, "pressure_mb": 1002.25, "precip_mm": 0.0, "humidity": 18.625, "cloud": 0.25, "feelslike_c": 33.0875, "will_it_rain": 0.0, "chance_of_rain": 0.0, "will_it_snow": 0.0, "chance_of_snow": 0.0, "vis_km": 10.0, "gust_kph": 9.45, "uv": 8.5}, {"hour": 10, "temp_c": 36.4625, "is_day": 1.0, "wind_kph": 8.325, "pressure_mb": 1002.125, "precip_mm": 0.0, "humidity": 16.375, "cloud": 0.125, "feelslike_c": 35.0875, "will_it_rain": 0.0, "chance_of_rain": 0.0, "will_it_snow": 0.0, "chance_of_snow": 0.0, "vis_km": 10.0, "gust_kph": 9.6, "uv": 9.0}, {"hour": 11, "temp_c": 40.800000000000004, "is_day": 1.0, "wind_kph": 9.2375, "pressure_mb": 1001.75, "precip_mm": 0.0, "humidity": 14.75, "cloud": 0.0, "feelslike_c": 41.15, "will_it_rain": 0.0, "chance_of_rain": 0.0, "will_it_snow": 0.0, "chance_of_snow": 0.0, "vis_km": 10.0, "gust_kph": 10.575, "uv": 9.625}, {"hour": 12, "temp_c": 41.9875, "is_day": 1.0, "wind_kph": 11.174999999999999, "pressure_mb": 1001.25, "precip_mm": 0.0, "humidity": 13.125, "cloud": 0.25, "feelslike_c": 42.975, "will_it_rain": 0.0, "chance_of_rain": 0.0, "will_it_snow": 0.0, "chance_of_snow": 0.0, "vis_km": 10.0, "gust_kph": 12.825, "uv": 10.0}, {"hour": 13, "temp_c": 42.925, "is_day": 1.0, "wind_kph": 12.9, "pressure_mb": 1000.75, "precip_mm": 0.0, "humidity": 11.625, "cloud": 0.75, "feelslike_c": 44.4875, "will_it_rain": 0.0, "chance_of_rain": 0.0, "will_it_snow": 0.0, "chance_of_snow": 0.0, "vis_km": 10.0, "gust_kph": 14.900000000000002, "uv": 10.0}, {"hour": 14, "temp_c": 43.4125, "is_day": 1.0, "wind_kph": 13.4, "pressure_mb": 1000.125, "precip_mm": 0.0, "humidity": 10.625, "cloud": 0.25, "feelslike_c": 45.2875, "will_it_rain": 0.0, "chance_of_rain": 0.0, "will_it_snow": 0.0, "chance_of_snow": 0.0, "vis_km": 10.0, "gust_kph": 15.424999999999999, "uv": 10.125}, {"hour": 15, "temp_c": 43.46249999999999, "is_day": 1.0, "wind_kph": 14.125, "pressure_mb": 999.625, "precip_mm": 0.0, "humidity": 10.125, "cloud": 0.0, "feelslike_c": 45.4, "will_it_rain": 0.0, "chance_of_rain": 0.0, "will_it_snow": 0.0, "chance_of_snow": 0.0, "vis_km": 10.0, "gust_kph": 16.25, "uv": 10.125}, {"hour": 16, "temp_c": 42.95, "is_day": 1.0, "wind_kph": 15.5625, "pressure_mb": 999.125, "precip_mm": 0.0, "humidity": 9.875, "cloud": 0.0, "feelslike_c": 44.537499999999994, "will_it_rain": 0.0, "chance_of_rain": 0.0, "will_it_snow": 0.0, "chance_of_snow": 0.0, "vis_km": 10.0, "gust_kph": 18.0, "uv": 10.0}, {"hour": 17, "temp_c": 42.087500000000006, "is_day": 1.0, "wind_kph": 16.925, "pressure_mb": 998.75, "precip_mm": 0.0, "humidity": 10.125, "cloud": 0.0, "feelslike_c": 43.15, "will_it_rain": 0.0, "chance_of_rain": 0.0, "will_it_snow": 0.0, "chance_of_snow": 0.0, "vis_km": 10.0, "gust_kph": 19.4375, "uv": 10.0}, {"hour": 18, "temp_c": 41.137499999999996, "is_day": 1.0, "wind_kph": 18.724999999999998, "pressure_mb": 998.75, "precip_mm": 0.0, "humidity": 10.25, "cloud": 0.0, "feelslike_c": 41.6625, "will_it_rain": 0.0, "chance_of_rain": 0.0, "will_it_snow": 0.0, "chance_of_snow": 0.0, "vis_km": 10.0, "gust_kph": 21.562499999999996, "uv": 9.75}, {"hour": 19, "temp_c": 39.05, "is_day": 1.0, "wind_kph": 19.7125, "pressure_mb": 999.375, "precip_mm": 0.0, "humidity": 11.5, "cloud": 0.0, "feelslike_c": 38.575, "will_it_rain": 0.0, "chance_of_rain": 0.0, "will_it_snow": 0.0, "chance_of_snow": 0.0, "vis_km": 10.0, "gust_kph": 24.925000000000004, "uv": 9.25}, {"hour": 20, "temp_c": 36.8125, "is_day": 0.0, "wind_kph": 19.35, "pressure_mb": 999.75, "precip_mm": 0.0, "humidity": 12.25, "cloud": 0.0, "feelslike_c": 35.4875, "will_it_rain": 0.0, "chance_of_rain": 0.0, "will_it_snow": 0.0, "chance_of_snow": 0.0, "vis_km": 10.0, "gust_kph": 31.900000000000002, "uv": 1.0}, {"hour": 21, "temp_c": 35.625, "is_day": 0.0, "wind_kph": 18.0, "pressure_mb": 1000.25, "precip_mm": 0.0, "humidity": 13.375, "cloud": 0.25, "feelslike_c": 33.9875, "will_it_rain": 0.0, "chance_of_rain": 0.0, "will_it_snow": 0.0, "chance_of_snow": 0.0, "vis_km": 10.0, "gust_kph": 32.275, "uv": 1.0}, {"hour": 22, "temp_c": 34.3625, "is_day": 0.0, "wind_kph": 16.3125, "pressure_mb": 1000.375, "precip_mm": 0.0, "humidity": 14.375, "cloud": 0.0, "feelslike_c": 32.45, "will_it_rain": 0.0, "chance_of_rain": 0.0, "will_it_snow": 0.0, "chance_of_snow": 0.0, "vis_km": 10.0, "gust_kph": 31.4, "uv": 1.0}, {"hour": 23, "temp_c": 33.199999999999996, "is_day": 0.0, "wind_kph": 14.725000000000001, "pressure_mb": 1000.5, "precip_mm": 0.0, "humidity": 15.125, "cloud": 0.0, "feelslike_c": 31.1125, "will_it_rain": 0.0, "chance_of_rain": 0.0, "will_it_snow": 0.0, "chance_of_snow": 0.0, "vis_km": 10.0, "gust_kph": 29.599999999999994, "uv": 1.0}]}