{"name": "Aguada De San Antonio", "region": "Guarico", "country": "Venezuela", "lat": 9.58, "lon": -67.43, "sunrise": 372, "sunset": 1133, "weather": [{"hour": 0, "temp_c": 20.474999999999998, "wind_kph": 2.7500000000000004, "pressure_mb": 1014.25, "precip_mm": 0.11249999999999999, "humidity": 94.125}, {"hour": 1, "temp_c": 20.262500000000003, "wind_kph": 3.0625, "pressure_mb": 1013.375, "precip_mm": 0.175, "humidity": 94.125}, {"hour": 2, "temp_c": 20.4375, "wind_kph": 3.05, "pressure_mb": 1012.875, "precip_mm": 0.75, "humidity": 94.25}, {"hour": 3, "temp_c": 20.275, "wind_kph": 2.9625, "pressure_mb": 1012.625, "precip_mm": 0.275, "humidity": 94.375}, {"hour": 4, "temp_c": 20.0875, "wind_kph": 2.875, "pressure_mb": 1012.75, "precip_mm": 0.3, "humidity": 94.75}, {"hour": 5, "temp_c": 20.125, "wind_kph": 2.85, "pressure_mb": 1013.0, "precip_mm": 0.8625, "humidity": 94.875}, {"hour": 6, "temp_c": 20.0625, "wind_kph": 3.0500000000000003, "pressure_mb": 1013.75, "precip_mm": 0.3, "humidity": 95.5}, {"hour": 7, "temp_c": 20.750000000000004, "wind_kph": 2.9250000000000003, "pressure_mb": 1014.0, "precip_mm": 0.3125, "humidity": 94.375}, {"hour": 8, "temp_c": 22.2125, "wind_kph": 3.275, "pressure_mb": 1014.625, "precip_mm": 2.0, "humidity": 90.625}, {"hour": 9, "temp_c": 23.9, "wind_kph": 3.7749999999999995, "pressure_mb": 1015.125, "precip_mm": 0.25, "humidity": 86.25}, {"hour": 10, "temp_c": 25.0125, "wind_kph": 5.2250000000000005, "pressure_mb": 1015.0, "precip_mm": 0.3, "humidity": 81.25}, {"hour": 11, "temp_c": 26.3125, "wind_kph": 6.6625, "pressure_mb": 1014.625, "precip_mm": 1.0250000000000001, "humidity": 78.0}, {"hour": 12, "temp_c": 26.487499999999997, "wind_kph": 7.375, "pressure_mb": 1014.25, "precip_mm": 0.41250000000000003, "humidity": 78.0}, {"hour": 13, "temp_c": 26.325, "wind_kph": 7.5375000000000005, "pressure_mb": 1013.5, "precip_mm": 0.4625, "humidity": 79.375}, {"hour": 14, "temp_c": 26.2, "wind_kph": 7.2, "pressure_mb": 1012.875, "precip_mm": 3.1125, "humidity": 79.625}, {"hour": 15, "temp_c": 25.812500000000004, "wind_kph": 6.15, "pressure_mb": 1012.125, "precip_mm": 0.7, "humidity": 81.125}, {"hour": 16, "temp_c": 25.3875, "wind_kph": 5.249999999999999, "pressure_mb": 1011.75, "precip_mm": 0.6499999999999999, "humidity": 82.625}, {"hour": 17, "temp_c": 24.925, "wind_kph": 5.0375000000000005, "pressure_mb": 1011.875, "precip_mm": 1.7625, "humidity": 85.375}, {"hour": 18, "temp_c": 24.150000000000002, "wind_kph": 3.9, "pressure_mb": 1012.375, "precip_mm": 0.55, "humidity": 90.625}, {"hour": 19, "temp_c": 22.8, "wind_kph": 2.8, "pressure_mb": 1013.125, "precip_mm": 0.5375, "humidity": 94.375}, {"hour": 20, "temp_c": 21.925, "wind_kph": 1.8875, "pressure_mb": 1013.625, "precip_mm": 3.0374999999999996, "humidity": 95.5}, {"hour": 21, "temp_c": 21.724999999999998, "wind_kph": 1.9625000000000001, "pressure_mb": 1014.375, "precip_mm": 0.275, "humidity": 95.5}, {"hour": 22, "temp_c": 20.837500000000002, "wind_kph": 2.3, "pressure_mb": 1014.5, "precip_mm": 0.2, "humidity": 94.875}, {"hour": 23, "temp_c": 20.699999999999996, "wind_kph": 2.7375000000000003, "pressure_mb": 1015.0, "precip_mm": 0.43750000000000006, "humidity": 94.875}]}