{"name": "La Noria", "region": "Sonora", "country": "Mexico", "lat": 31.48, "lon": -110.69, "sunrise": 320, "sunset": 1171, "weather": [{"hour": 0, "temp_c": 22.4375, "wind_kph": 3.5124999999999997, "pressure_mb": 1012.5, "precip_mm": 0.0, "humidity": 24.625}, {"hour": 1, "temp_c": 20.200000000000003, "wind_kph": 4.612500000000001, "pressure_mb": 1012.125, "precip_mm": 0.0, "humidity": 26.75}, {"hour": 2, "temp_c": 19.724999999999998, "wind_kph": 3.775, "pressure_mb": 1012.0, "precip_mm": 0.0, "humidity": 27.875}, {"hour": 3, "temp_c": 19.8125, "wind_kph": 4.45, "pressure_mb": 1012.875, "precip_mm": 0.0, "humidity": 29.375}, {"hour": 4, "temp_c": 19.1125, "wind_kph": 5.075, "pressure_mb": 1011.5, "precip_mm": 0.0, "humidity": 29.25}, {"hour": 5, "temp_c": 18.849999999999998, "wind_kph": 5.4125, "pressure_mb": 1011.75, "precip_mm": 0.0, "humidity": 30.125}, {"hour": 6, "temp_c": 18.0375, "wind_kph": 6.125, "pressure_mb": 1013.5, "precip_mm": 0.0, "humidity": 33.75}, {"hour": 7, "temp_c": 20.5125, "wind_kph": 6.5625, "pressure_mb": 1012.375, "precip_mm": 0.0, "humidity": 31.25}, {"hour": 8, "temp_c": 25.199999999999996, "wind_kph": 6.225, "pressure_mb": 1012.875, "precip_mm": 0.0, "humidity": 22.875}, {"hour": 9, "temp_c": 28.5625, "wind_kph": 6.062499999999999, "pressure_mb": 1012.5, "precip_mm": 0.0, "humidity": 20.75}, {"hour": 10, "temp_c": 30.387499999999996, "wind_kph": 7.8875, "pressure_mb": 1012.0, "precip_mm": 0.0, "humidity": 14.5}, {"hour": 11, "temp_c": 35.1125, "wind_kph": 11.774999999999997, "pressure_mb": 1011.5, "precip_mm": 0.0, "humidity": 12.75}, {"hour": 12, "temp_c": 36.862500000000004, "wind_kph": 16.8375, "pressure_mb": 1011.5, "precip_mm": 0.0, "humidity": 14.375}, {"hour": 13, "temp_c": 36.275000000000006, "wind_kph": 21.037499999999998, "pressure_mb": 1010.5, "precip_mm": 0.0, "humidity": 11.75}, {"hour": 14, "temp_c": 36.4375, "wind_kph": 23.9, "pressure_mb": 1009.625, "precip_mm": 0.0, "humidity": 11.625}, {"hour": 15, "temp_c": 37.5, "wind_kph": 26.462500000000002, "pressure_mb": 1009.875, "precip_mm": 0.0, "humidity": 12.75}, {"hour": 16, "temp_c": 36.0625, "wind_kph": 28.975, "pressure_mb": 1008.125, "precip_mm": 0.0, "humidity": 10.75}, {"hour": 17, "temp_c": 35.262499999999996, "wind_kph": 30.000000000000004, "pressure_mb": 1008.0, "precip_mm": 0.0, "humidity": 10.875}, {"hour": 18, "temp_c": 34.75, "wind_kph": 29.112499999999997, "pressure_mb": 1008.875, "precip_mm": 0.0, "humidity": 12.25}, {"hour": 19, "temp_c": 32.55, "wind_kph": 28.075, "pressure_mb": 1007.875, "precip_mm": 0.0, "humidity": 12.75}, {"hour": 20, "temp_c": 29.7, "wind_kph": 23.587500000000002, "pressure_mb": 1008.625, "precip_mm": 0.0, "humidity": 15.5}, {"hour": 21, "temp_c": 25.875, "wind_kph": 14.387500000000001, "pressure_mb": 1010.375, "precip_mm": 0.0, "humidity": 19.875}, {"hour": 22, "temp_c": 23.175, "wind_kph": 8.175, "pressure_mb": 1010.625, "precip_mm": 0.0, "humidity": 22.75}, {"hour": 23, "temp_c": 21.662499999999998, "wind_kph": 5.137500000000001, "pressure_mb": 1011.375, "precip_mm": 0.0, "humidity": 26.25}]}