{"name": "Ban Phaet", "region": "Chai Nat", "country": "Thailand", "lat": 15.0, "lon": 99.91, "sunrise": 353, "sunset": 1133, "weather": [{"hour": 0, "temp_c": 28.162499999999994, "wind_kph": 8.8625, "pressure_mb": 1007.0, "precip_mm": 0.0625, "humidity": 66.375}, {"hour": 1, "temp_c": 27.862499999999997, "wind_kph": 9.325, "pressure_mb": 1006.625, "precip_mm": 0.125, "humidity": 67.5}, {"hour": 2, "temp_c": 27.5375, "wind_kph": 9.45, "pressure_mb": 1006.0, "precip_mm": 0.0125, "humidity": 68.75}, {"hour": 3, "temp_c": 27.2125, "wind_kph": 8.95, "pressure_mb": 1005.625, "precip_mm": 0.0, "humidity": 70.0}, {"hour": 4, "temp_c": 26.9375, "wind_kph": 8.5125, "pressure_mb": 1005.875, "precip_mm": 0.0125, "humidity": 71.5}, {"hour": 5, "temp_c": 26.637500000000003, "wind_kph": 8.4625, "pressure_mb": 1006.125, "precip_mm": 0.0, "humidity": 72.75}, {"hour": 6, "temp_c": 26.45, "wind_kph": 7.9625, "pressure_mb": 1006.375, "precip_mm": 0.0, "humidity": 73.75}, {"hour": 7, "temp_c": 27.562499999999996, "wind_kph": 8.1375, "pressure_mb": 1007.125, "precip_mm": 0.0, "humidity": 70.125}, {"hour": 8, "temp_c": 29.35, "wind_kph": 9.950000000000001, "pressure_mb": 1007.75, "precip_mm": 0.0, "humidity": 62.625}, {"hour": 9, "temp_c": 31.275000000000002, "wind_kph": 10.1625, "pressure_mb": 1008.0, "precip_mm": 0.0, "humidity": 55.375}, {"hour": 10, "temp_c": 33.0625, "wind_kph": 10.1625, "pressure_mb": 1008.0, "precip_mm": 0.0, "humidity": 48.875}, {"hour": 11, "temp_c": 36.037499999999994, "wind_kph": 10.700000000000001, "pressure_mb": 1007.25, "precip_mm": 0.0, "humidity": 44.0}, {"hour": 12, "temp_c": 36.775, "wind_kph": 11.65, "pressure_mb": 1006.375, "precip_mm": 0.0, "humidity": 40.25}, {"hour": 13, "temp_c": 37.449999999999996, "wind_kph": 12.3125, "pressure_mb": 1005.25, "precip_mm": 0.0, "humidity": 37.625}, {"hour": 14, "temp_c": 37.5375, "wind_kph": 13.325000000000001, "pressure_mb": 1004.0, "precip_mm": 0.05, "humidity": 37.125}, {"hour": 15, "temp_c": 36.625, "wind_kph": 12.8625, "pressure_mb": 1003.375, "precip_mm": 0.0125, "humidity": 39.125}, {"hour": 16, "temp_c": 35.525, "wind_kph": 12.875, "pressure_mb": 1002.75, "precip_mm": 0.1375, "humidity": 42.0}, {"hour": 17, "temp_c": 34.612500000000004, "wind_kph": 13.0, "pressure_mb": 1002.875, "precip_mm": 0.0, "humidity": 44.375}, {"hour": 18, "temp_c": 33.425, "wind_kph": 12.4, "pressure_mb": 1003.75, "precip_mm": 0.037500000000000006, "humidity": 48.125}, {"hour": 19, "temp_c": 31.35, "wind_kph": 12.450000000000001, "pressure_mb": 1004.5, "precip_mm": 0.11249999999999999, "humidity": 54.875}, {"hour": 20, "temp_c": 30.262499999999996, "wind_kph": 12.424999999999999, "pressure_mb": 1005.5, "precip_mm": 0.18750000000000003, "humidity": 59.875}, {"hour": 21, "temp_c": 29.550000000000004, "wind_kph": 11.725, "pressure_mb": 1006.5, "precip_mm": 0.125, "humidity": 63.5}, {"hour": 22, "temp_c": 29.125, "wind_kph": 10.575, "pressure_mb": 1006.875, "precip_mm": 0.35000000000000003, "humidity": 65.625}, {"hour": 23, "temp_c": 28.925, "wind_kph": 10.225000000000001, "pressure_mb": 1007.0, "precip_mm": 0.0875, "humidity": 66.5}]}