{"name": "Naykol'", "region": "Bamian", "country": "Afghanistan", "lat": 34.05, "lon": 67.1, "sunrise": 292, "sunset": 1157, "weather": [{"hour": 0, "temp_c": 13.075, "wind_kph": 7.8375, "pressure_mb": 1011.5, "precip_mm": 0.0, "humidity": 32.875}, {"hour": 1, "temp_c": 11.987499999999999, "wind_kph": 8.025, "pressure_mb": 1011.375, "precip_mm": 0.0, "humidity": 34.375}, {"hour": 2, "temp_c": 10.9875, "wind_kph": 7.7, "pressure_mb": 1011.375, "precip_mm": 0.0, "humidity": 35.875}, {"hour": 3, "temp_c": 10.575000000000001, "wind_kph": 7.825, "pressure_mb": 1011.875, "precip_mm": 0.0, "humidity": 37.5}, {"hour": 4, "temp_c": 11.575000000000001, "wind_kph": 7.9875, "pressure_mb": 1012.0, "precip_mm": 0.0, "humidity": 39.125}, {"hour": 5, "temp_c": 11.924999999999999, "wind_kph": 7.737500000000001, "pressure_mb": 1012.625, "precip_mm": 0.0, "humidity": 39.875}, {"hour": 6, "temp_c": 14.000000000000002, "wind_kph": 6.687499999999999, "pressure_mb": 1012.5, "precip_mm": 0.0, "humidity": 34.0}, {"hour": 7, "temp_c": 16.1, "wind_kph": 6.1, "pressure_mb": 1011.5, "precip_mm": 0.0, "humidity": 28.5}, {"hour": 8, "temp_c": 18.162499999999998, "wind_kph": 5.85, "pressure_mb": 1010.125, "precip_mm": 0.0, "humidity": 23.375}, {"hour": 9, "temp_c": 20.1125, "wind_kph": 8.0125, "pressure_mb": 1009.125, "precip_mm": 0.0, "humidity": 18.25}, {"hour": 10, "temp_c": 21.7, "wind_kph": 9.5125, "pressure_mb": 1008.0, "precip_mm": 0.0, "humidity": 15.375}, {"hour": 11, "temp_c": 24.4375, "wind_kph": 11.05, "pressure_mb": 1007.0, "precip_mm": 0.0, "humidity": 13.125}, {"hour": 12, "temp_c": 26.3125, "wind_kph": 12.700000000000001, "pressure_mb": 1006.25, "precip_mm": 0.0, "humidity": 12.125}, {"hour": 13, "temp_c": 27.624999999999996, "wind_kph": 14.9375, "pressure_mb": 1005.5, "precip_mm": 0.0, "humidity": 11.25}, {"hour": 14, "temp_c": 28.0125, "wind_kph": 15.8, "pressure_mb": 1004.75, "precip_mm": 0.0, "humidity": 11.125}, {"hour": 15, "temp_c": 27.599999999999998, "wind_kph": 15.537499999999998, "pressure_mb": 1004.25, "precip_mm": 0.0, "humidity": 11.5}, {"hour": 16, "temp_c": 27.050000000000004, "wind_kph": 18.812499999999996, "pressure_mb": 1004.125, "precip_mm": 0.0, "humidity": 11.75}, {"hour": 17, "temp_c": 26.125, "wind_kph": 19.275000000000002, "pressure_mb": 1004.375, "precip_mm": 0.0, "humidity": 12.875}, {"hour": 18, "temp_c": 24.1625, "wind_kph": 19.35, "pressure_mb": 1005.25, "precip_mm": 0.0, "humidity": 16.125}, {"hour": 19, "temp_c": 21.200000000000003, "wind_kph": 16.075000000000003, "pressure_mb": 1007.125, "precip_mm": 0.0, "humidity": 20.375}, {"hour": 20, "temp_c": 17.2375, "wind_kph": 12.5, "pressure_mb": 1008.875, "precip_mm": 0.0, "humidity": 23.25}, {"hour": 21, "temp_c": 16.0125, "wind_kph": 10.25, "pressure_mb": 1010.25, "precip_mm": 0.0, "humidity": 26.125}, {"hour": 22, "temp_c": 14.8125, "wind_kph": 9.325000000000001, "pressure_mb": 1010.75, "precip_mm": 0.0, "humidity": 28.75}, {"hour": 23, "temp_c": 13.825000000000001, "wind_kph": 8.674999999999999, "pressure_mb": 1011.375, "precip_mm": 0.0, "humidity": 30.625}]}