{"name": "Hlao", "region": "Chiang Mai", "country": "Thailand", "lat": 19.43, "lon": 99.25, "sunrise": 347, "sunset": 1145, "weather": [{"hour": 0, "temp_c": 21.375, "wind_kph": 4.55, "pressure_mb": 1007.25, "precip_mm": 0.3125, "humidity": 95.75}, {"hour": 1, "temp_c": 21.375000000000004, "wind_kph": 4.25, "pressure_mb": 1006.875, "precip_mm": 1.5374999999999999, "humidity": 96.0}, {"hour": 2, "temp_c": 21.499999999999996, "wind_kph": 4.05, "pressure_mb": 1006.25, "precip_mm": 0.3, "humidity": 96.125}, {"hour": 3, "temp_c": 21.5875, "wind_kph": 4.0625, "pressure_mb": 1006.125, "precip_mm": 0.2625, "humidity": 96.375}, {"hour": 4, "temp_c": 21.650000000000002, "wind_kph": 3.875, "pressure_mb": 1006.375, "precip_mm": 0.9874999999999999, "humidity": 96.5}, {"hour": 5, "temp_c": 21.762500000000003, "wind_kph": 3.7375000000000003, "pressure_mb": 1006.625, "precip_mm": 0.3125, "humidity": 97.125}, {"hour": 6, "temp_c": 21.8125, "wind_kph": 3.275, "pressure_mb": 1007.125, "precip_mm": 0.3625, "humidity": 97.125}, {"hour": 7, "temp_c": 22.2625, "wind_kph": 3.0, "pressure_mb": 1007.75, "precip_mm": 1.6625, "humidity": 95.875}, {"hour": 8, "temp_c": 23.8875, "wind_kph": 3.0625, "pressure_mb": 1008.25, "precip_mm": 0.2, "humidity": 93.0}, {"hour": 9, "temp_c": 25.262499999999996, "wind_kph": 3.35, "pressure_mb": 1008.5, "precip_mm": 0.2125, "humidity": 87.625}, {"hour": 10, "temp_c": 26.625000000000004, "wind_kph": 4.175, "pressure_mb": 1008.25, "precip_mm": 0.7625, "humidity": 81.375}, {"hour": 11, "temp_c": 28.562499999999996, "wind_kph": 4.4125000000000005, "pressure_mb": 1007.75, "precip_mm": 0.1875, "humidity": 75.625}, {"hour": 12, "temp_c": 29.4625, "wind_kph": 4.7, "pressure_mb": 1006.875, "precip_mm": 0.23750000000000002, "humidity": 71.25}, {"hour": 13, "temp_c": 29.95, "wind_kph": 5.3625, "pressure_mb": 1005.75, "precip_mm": 0.9750000000000001, "humidity": 69.0}, {"hour": 14, "temp_c": 29.9125, "wind_kph": 5.675, "pressure_mb": 1004.875, "precip_mm": 0.4874999999999999, "humidity": 69.625}, {"hour": 15, "temp_c": 29.599999999999998, "wind_kph": 5.6125, "pressure_mb": 1004.375, "precip_mm": 0.33749999999999997, "humidity": 71.75}, {"hour": 16, "temp_c": 29.5875, "wind_kph": 5.8375, "pressure_mb": 1003.625, "precip_mm": 1.5000000000000002, "humidity": 71.125}, {"hour": 17, "temp_c": 29.074999999999996, "wind_kph": 6.05, "pressure_mb": 1003.5, "precip_mm": 0.31250000000000006, "humidity": 73.0}, {"hour": 18, "temp_c": 27.6875, "wind_kph": 5.875, "pressure_mb": 1004.0, "precip_mm": 0.45, "humidity": 80.125}, {"hour": 19, "temp_c": 25.6375, "wind_kph": 5.725, "pressure_mb": 1004.875, "precip_mm": 2.15, "humidity": 87.5}, {"hour": 20, "temp_c": 24.6625, "wind_kph": 5.574999999999999, "pressure_mb": 1005.875, "precip_mm": 0.42500000000000004, "humidity": 90.875}, {"hour": 21, "temp_c": 24.2, "wind_kph": 5.2749999999999995, "pressure_mb": 1006.625, "precip_mm": 0.30000000000000004, "humidity": 92.5}, {"hour": 22, "temp_c": 23.0125, "wind_kph": 5.0375, "pressure_mb": 1007.25, "precip_mm": 1.0, "humidity": 93.125}, {"hour": 23, "temp_c": 22.425, "wind_kph": 4.55, "pressure_mb": 1007.375, "precip_mm": 0.25000000000000006, "humidity": 93.625}]}