{"name": "White Mesa", "region": "Utah", "country": "United States of America", "lat": 37.48, "lon": -109.56, "sunrise": 359, "sunset": 1243, "weather": [{"hour": 0, "temp_c": 17.525000000000002, "wind_kph": 10.4375, "pressure_mb": 1012.25, "precip_mm": 0.0, "humidity": 21.0}, {"hour": 1, "temp_c": 16.8125, "wind_kph": 8.1, "pressure_mb": 1012.0, "precip_mm": 0.0, "humidity": 19.875}, {"hour": 2, "temp_c": 16.15, "wind_kph": 6.975, "pressure_mb": 1012.125, "precip_mm": 0.0, "humidity": 21.125}, {"hour": 3, "temp_c": 14.875000000000002, "wind_kph": 6.525, "pressure_mb": 1013.5, "precip_mm": 0.0, "humidity": 26.125}, {"hour": 4, "temp_c": 14.850000000000001, "wind_kph": 6.612500000000001, "pressure_mb": 1012.375, "precip_mm": 0.0, "humidity": 23.5}, {"hour": 5, "temp_c": 14.25, "wind_kph": 6.6625, "pressure_mb": 1012.875, "precip_mm": 0.0, "humidity": 24.5}, {"hour": 6, "temp_c": 11.8875, "wind_kph": 6.3875, "pressure_mb": 1015.125, "precip_mm": 0.0, "humidity": 32.625}, {"hour": 7, "temp_c": 15.725000000000001, "wind_kph": 5.675, "pressure_mb": 1014.125, "precip_mm": 0.0, "humidity": 26.875}, {"hour": 8, "temp_c": 19.225, "wind_kph": 6.3374999999999995, "pressure_mb": 1014.0, "precip_mm": 0.0, "humidity": 20.625}, {"hour": 9, "temp_c": 19.337500000000002, "wind_kph": 11.0625, "pressure_mb": 1014.875, "precip_mm": 0.0, "humidity": 23.375}, {"hour": 10, "temp_c": 22.900000000000002, "wind_kph": 14.6125, "pressure_mb": 1013.375, "precip_mm": 0.0, "humidity": 15.875}, {"hour": 11, "temp_c": 24.975, "wind_kph": 17.099999999999998, "pressure_mb": 1012.75, "precip_mm": 0.0, "humidity": 14.25}, {"hour": 12, "temp_c": 25.825, "wind_kph": 19.475000000000005, "pressure_mb": 1012.5, "precip_mm": 0.0, "humidity": 14.375}, {"hour": 13, "temp_c": 27.7125, "wind_kph": 21.5, "pressure_mb": 1011.25, "precip_mm": 0.0, "humidity": 11.75}, {"hour": 14, "temp_c": 28.4875, "wind_kph": 21.8125, "pressure_mb": 1010.125, "precip_mm": 0.0, "humidity": 10.875}, {"hour": 15, "temp_c": 28.725, "wind_kph": 23.212500000000002, "pressure_mb": 1010.25, "precip_mm": 0.0, "humidity": 10.75}, {"hour": 16, "temp_c": 29.599999999999998, "wind_kph": 25.925, "pressure_mb": 1008.375, "precip_mm": 0.0, "humidity": 9.5}, {"hour": 17, "temp_c": 29.487499999999997, "wind_kph": 27.0, "pressure_mb": 1007.875, "precip_mm": 0.0, "humidity": 9.375}, {"hour": 18, "temp_c": 28.937500000000004, "wind_kph": 27.537499999999998, "pressure_mb": 1008.0, "precip_mm": 0.0, "humidity": 9.375}, {"hour": 19, "temp_c": 28.15, "wind_kph": 26.775, "pressure_mb": 1007.125, "precip_mm": 0.0, "humidity": 10.625}, {"hour": 20, "temp_c": 25.525, "wind_kph": 20.525000000000002, "pressure_mb": 1007.75, "precip_mm": 0.0, "humidity": 13.625}, {"hour": 21, "temp_c": 21.925, "wind_kph": 16.7375, "pressure_mb": 1009.875, "precip_mm": 0.0, "humidity": 18.625}, {"hour": 22, "temp_c": 20.525, "wind_kph": 13.9125, "pressure_mb": 1010.0, "precip_mm": 0.0, "humidity": 17.375}, {"hour": 23, "temp_c": 19.5625, "wind_kph": 12.2375, "pressure_mb": 1010.5, "precip_mm": 0.0, "humidity": 17.375}]}