{"name": "Bogodukhovka", "region": "Zhambyl", "country": "Kazakhstan", "lat": 44.92, "lon": 74.24, "sunrise": 318, "sunset": 1253, "weather": [{"hour": 0, "temp_c": 21.8125, "wind_kph": 15.475000000000001, "pressure_mb": 1008.375, "precip_mm": 0.0, "humidity": 36.75}, {"hour": 1, "temp_c": 21.275000000000002, "wind_kph": 14.0625, "pressure_mb": 1008.125, "precip_mm": 0.0, "humidity": 37.0}, {"hour": 2, "temp_c": 20.812499999999996, "wind_kph": 12.5125, "pressure_mb": 1008.25, "precip_mm": 0.0, "humidity": 37.375}, {"hour": 3, "temp_c": 20.4375, "wind_kph": 12.6375, "pressure_mb": 1008.375, "precip_mm": 0.0, "humidity": 37.875}, {"hour": 4, "temp_c": 19.974999999999998, "wind_kph": 13.925, "pressure_mb": 1008.75, "precip_mm": 0.0, "humidity": 39.125}, {"hour": 5, "temp_c": 19.3375, "wind_kph": 13.912500000000001, "pressure_mb": 1009.125, "precip_mm": 0.0, "humidity": 40.75}, {"hour": 6, "temp_c": 19.3, "wind_kph": 14.3125, "pressure_mb": 1009.5, "precip_mm": 0.0, "humidity": 41.75}, {"hour": 7, "temp_c": 20.0875, "wind_kph": 14.6625, "pressure_mb": 1009.875, "precip_mm": 0.0, "humidity": 39.875}, {"hour": 8, "temp_c": 21.2, "wind_kph": 15.65, "pressure_mb": 1010.375, "precip_mm": 0.0, "humidity": 38.0}, {"hour": 9, "temp_c": 22.462499999999995, "wind_kph": 14.762500000000001, "pressure_mb": 1010.375, "precip_mm": 0.0, "humidity": 35.5}, {"hour": 10, "temp_c": 23.599999999999998, "wind_kph": 13.825, "pressure_mb": 1010.125, "precip_mm": 0.0, "humidity": 32.625}, {"hour": 11, "temp_c": 24.850000000000005, "wind_kph": 14.662500000000001, "pressure_mb": 1009.75, "precip_mm": 0.0, "humidity": 31.5}, {"hour": 12, "temp_c": 25.362499999999997, "wind_kph": 16.375, "pressure_mb": 1009.5, "precip_mm": 0.0, "humidity": 31.125}, {"hour": 13, "temp_c": 25.7875, "wind_kph": 18.537499999999998, "pressure_mb": 1009.125, "precip_mm": 0.0, "humidity": 30.75}, {"hour": 14, "temp_c": 26.2, "wind_kph": 20.637500000000003, "pressure_mb": 1008.375, "precip_mm": 0.0, "humidity": 30.25}, {"hour": 15, "temp_c": 26.4875, "wind_kph": 22.5875, "pressure_mb": 1008.25, "precip_mm": 0.0, "humidity": 29.5}, {"hour": 16, "temp_c": 26.599999999999998, "wind_kph": 23.925, "pressure_mb": 1007.875, "precip_mm": 0.0, "humidity": 29.25}, {"hour": 17, "temp_c": 26.45, "wind_kph": 24.9625, "pressure_mb": 1007.375, "precip_mm": 0.0, "humidity": 29.25}, {"hour": 18, "temp_c": 26.0875, "wind_kph": 24.4875, "pressure_mb": 1007.625, "precip_mm": 0.0, "humidity": 29.375}, {"hour": 19, "temp_c": 25.775000000000002, "wind_kph": 22.912499999999998, "pressure_mb": 1007.75, "precip_mm": 0.0, "humidity": 30.25}, {"hour": 20, "temp_c": 24.85, "wind_kph": 19.25, "pressure_mb": 1008.0, "precip_mm": 0.0, "humidity": 31.875}, {"hour": 21, "temp_c": 23.6125, "wind_kph": 16.925, "pressure_mb": 1008.375, "precip_mm": 0.0, "humidity": 33.625}, {"hour": 22, "temp_c": 22.9375, "wind_kph": 16.125, "pressure_mb": 1008.75, "precip_mm": 0.0, "humidity": 34.125}, {"hour": 23, "temp_c": 22.450000000000003, "wind_kph": 15.862499999999999, "pressure_mb": 1008.625, "precip_mm": 0.0, "humidity": 35.0}]}