{"name": "Al Badi'", "region": "Al Bahah", "country": "Saudi Arabia", "lat": 22.58, "lon": 44.07, "sunrise": 321, "sunset": 1132, "weather": [{"hour": 0, "temp_c": 33.012499999999996, "wind_kph": 15.487499999999997, "pressure_mb": 1004.125, "precip_mm": 0.0, "humidity": 10.0}, {"hour": 1, "temp_c": 32.4125, "wind_kph": 15.487499999999997, "pressure_mb": 1003.75, "precip_mm": 0.0, "humidity": 10.5}, {"hour": 2, "temp_c": 31.7875, "wind_kph": 15.2375, "pressure_mb": 1003.25, "precip_mm": 0.0, "humidity": 10.875}, {"hour": 3, "temp_c": 31.224999999999998, "wind_kph": 14.412500000000001, "pressure_mb": 1003.375, "precip_mm": 0.0, "humidity": 11.125}, {"hour": 4, "temp_c": 30.65, "wind_kph": 14.075000000000001, "pressure_mb": 1004.0, "precip_mm": 0.0, "humidity": 11.375}, {"hour": 5, "temp_c": 30.0125, "wind_kph": 12.1625, "pressure_mb": 1004.625, "precip_mm": 0.0, "humidity": 11.875}, {"hour": 6, "temp_c": 30.162499999999998, "wind_kph": 10.7375, "pressure_mb": 1005.625, "precip_mm": 0.0, "humidity": 11.75}, {"hour": 7, "temp_c": 32.5625, "wind_kph": 9.499999999999998, "pressure_mb": 1005.875, "precip_mm": 0.0, "humidity": 10.125}, {"hour": 8, "temp_c": 34.99999999999999, "wind_kph": 10.387500000000001, "pressure_mb": 1005.625, "precip_mm": 0.0, "humidity": 8.625}, {"hour": 9, "temp_c": 36.8, "wind_kph": 11.462500000000002, "pressure_mb": 1005.5, "precip_mm": 0.0, "humidity": 7.75}, {"hour": 10, "temp_c": 37.5625, "wind_kph": 12.162500000000001, "pressure_mb": 1005.125, "precip_mm": 0.0, "humidity": 7.125}, {"hour": 11, "temp_c": 41.349999999999994, "wind_kph": 11.7375, "pressure_mb": 1004.625, "precip_mm": 0.0, "humidity": 6.5}, {"hour": 12, "temp_c": 42.2, "wind_kph": 11.162500000000001, "pressure_mb": 1003.625, "precip_mm": 0.0, "humidity": 6.25}, {"hour": 13, "temp_c": 42.712500000000006, "wind_kph": 11.762500000000001, "pressure_mb": 1002.75, "precip_mm": 0.0, "humidity": 6.125}, {"hour": 14, "temp_c": 42.8625, "wind_kph": 13.674999999999999, "pressure_mb": 1002.0, "precip_mm": 0.0, "humidity": 6.0}, {"hour": 15, "temp_c": 42.75, "wind_kph": 16.075, "pressure_mb": 1001.5, "precip_mm": 0.0, "humidity": 5.875}, {"hour": 16, "temp_c": 42.237500000000004, "wind_kph": 18.1375, "pressure_mb": 1001.0, "precip_mm": 0.0, "humidity": 5.75}, {"hour": 17, "temp_c": 41.400000000000006, "wind_kph": 19.575000000000003, "pressure_mb": 1001.0, "precip_mm": 0.0, "humidity": 5.875}, {"hour": 18, "temp_c": 40.112500000000004, "wind_kph": 20.037499999999998, "pressure_mb": 1001.375, "precip_mm": 0.0, "humidity": 6.25}, {"hour": 19, "temp_c": 37.95, "wind_kph": 18.0125, "pressure_mb": 1002.125, "precip_mm": 0.0, "humidity": 7.5}, {"hour": 20, "temp_c": 36.337500000000006, "wind_kph": 17.4875, "pressure_mb": 1003.125, "precip_mm": 0.0, "humidity": 8.125}, {"hour": 21, "temp_c": 35.4625, "wind_kph": 16.7375, "pressure_mb": 1003.625, "precip_mm": 0.0, "humidity": 8.625}, {"hour": 22, "temp_c": 34.825, "wind_kph": 16.924999999999997, "pressure_mb": 1003.875, "precip_mm": 0.0, "humidity": 9.0}, {"hour": 23, "temp_c": 34.15, "wind_kph": 17.3625, "pressure_mb": 1003.875, "precip_mm": 0.0, "humidity": 9.375}]}