{"name": "Gurvan-Tes", "region": "Bayanhongor", "country": "Mongolia", "lat": 44.25, "lon": 101.33, "sunrise": 333, "sunset": 1262, "weather": [{"hour": 0, "temp_c": 22.437499999999996, "wind_kph": 25.6125, "pressure_mb": 1004.0, "precip_mm": 0.0375, "humidity": 21.75}, {"hour": 1, "temp_c": 24.025000000000002, "wind_kph": 25.099999999999998, "pressure_mb": 1003.75, "precip_mm": 0.0375, "humidity": 20.625}, {"hour": 2, "temp_c": 25.700000000000003, "wind_kph": 26.137499999999996, "pressure_mb": 1003.75, "precip_mm": 0.0, "humidity": 17.5}, {"hour": 3, "temp_c": 26.8625, "wind_kph": 28.175, "pressure_mb": 1003.5, "precip_mm": 0.0375, "humidity": 15.875}, {"hour": 4, "temp_c": 27.950000000000003, "wind_kph": 28.2125, "pressure_mb": 1003.25, "precip_mm": 0.0, "humidity": 14.5}, {"hour": 5, "temp_c": 28.737499999999994, "wind_kph": 28.125, "pressure_mb": 1002.625, "precip_mm": 0.0125, "humidity": 12.75}, {"hour": 6, "temp_c": 29.525, "wind_kph": 26.837500000000002, "pressure_mb": 1001.75, "precip_mm": 0.0, "humidity": 11.625}, {"hour": 7, "temp_c": 30.35, "wind_kph": 25.1, "pressure_mb": 1000.875, "precip_mm": 0.0, "humidity": 10.125}, {"hour": 8, "temp_c": 30.825000000000003, "wind_kph": 25.525000000000002, "pressure_mb": 1000.5, "precip_mm": 0.0, "humidity": 8.5}, {"hour": 9, "temp_c": 30.7625, "wind_kph": 26.487499999999997, "pressure_mb": 1000.125, "precip_mm": 0.0, "humidity": 8.75}, {"hour": 10, "temp_c": 29.950000000000003, "wind_kph": 27.1125, "pressure_mb": 999.875, "precip_mm": 0.0, "humidity": 8.625}, {"hour": 11, "temp_c": 29.225, "wind_kph": 24.5375, "pressure_mb": 1000.125, "precip_mm": 0.0, "humidity": 8.625}, {"hour": 12, "temp_c": 28.5125, "wind_kph": 23.05, "pressure_mb": 1000.125, "precip_mm": 0.0, "humidity": 8.75}, {"hour": 13, "temp_c": 26.237499999999997, "wind_kph": 19.8875, "pressure_mb": 1000.875, "precip_mm": 0.0, "humidity": 10.125}, {"hour": 14, "temp_c": 25.062499999999996, "wind_kph": 17.624999999999996, "pressure_mb": 1001.5, "precip_mm": 0.0, "humidity": 11.25}, {"hour": 15, "temp_c": 24.099999999999998, "wind_kph": 15.475, "pressure_mb": 1001.875, "precip_mm": 0.0, "humidity": 12.0}, {"hour": 16, "temp_c": 23.3375, "wind_kph": 14.762500000000001, "pressure_mb": 1001.875, "precip_mm": 0.0, "humidity": 12.625}, {"hour": 17, "temp_c": 22.7125, "wind_kph": 14.925, "pressure_mb": 1002.125, "precip_mm": 0.0, "humidity": 12.625}, {"hour": 18, "temp_c": 22.012500000000003, "wind_kph": 13.6875, "pressure_mb": 1002.125, "precip_mm": 0.0, "humidity": 13.125}, {"hour": 19, "temp_c": 21.525000000000002, "wind_kph": 12.325, "pressure_mb": 1002.125, "precip_mm": 0.0, "humidity": 13.125}, {"hour": 20, "temp_c": 21.125, "wind_kph": 13.9125, "pressure_mb": 1002.375, "precip_mm": 0.0, "humidity": 13.875}, {"hour": 21, "temp_c": 20.525, "wind_kph": 15.374999999999998, "pressure_mb": 1002.75, "precip_mm": 0.0, "humidity": 16.125}, {"hour": 22, "temp_c": 19.825, "wind_kph": 19.025000000000002, "pressure_mb": 1003.5, "precip_mm": 0.0125, "humidity": 19.25}, {"hour": 23, "temp_c": 21.7, "wind_kph": 19.3125, "pressure_mb": 1003.75, "precip_mm": 0.0125, "humidity": 17.375}]}