{"name": "Yaptiksalya", "region": "Yamal-Nenets", "country": "Russia", "lat": 69.48, "lon": 72.23, "sunrise": 720, "sunset": 720, "weather": [{"hour": 0, "temp_c": 2.2749999999999995, "wind_kph": 15.649999999999999, "pressure_mb": 1009.5, "precip_mm": 0.0125, "humidity": 81.5}, {"hour": 1, "temp_c": 1.9875, "wind_kph": 15.337499999999999, "pressure_mb": 1009.5, "precip_mm": 0.0, "humidity": 82.375}, {"hour": 2, "temp_c": 1.8749999999999998, "wind_kph": 14.987500000000002, "pressure_mb": 1009.625, "precip_mm": 0.0125, "humidity": 82.75}, {"hour": 3, "temp_c": 1.7875, "wind_kph": 15.862499999999999, "pressure_mb": 1009.75, "precip_mm": 0.0, "humidity": 82.75}, {"hour": 4, "temp_c": 1.7, "wind_kph": 16.4375, "pressure_mb": 1009.75, "precip_mm": 0.0125, "humidity": 83.0}, {"hour": 5, "temp_c": 1.6874999999999998, "wind_kph": 16.287499999999998, "pressure_mb": 1009.875, "precip_mm": 0.075, "humidity": 83.375}, {"hour": 6, "temp_c": 1.675, "wind_kph": 16.037499999999998, "pressure_mb": 1009.875, "precip_mm": 0.0625, "humidity": 83.375}, {"hour": 7, "temp_c": 1.85, "wind_kph": 15.925, "pressure_mb": 1009.875, "precip_mm": 0.0625, "humidity": 82.875}, {"hour": 8, "temp_c": 2.0374999999999996, "wind_kph": 15.7875, "pressure_mb": 1009.875, "precip_mm": 0.1875, "humidity": 82.0}, {"hour": 9, "temp_c": 2.2375, "wind_kph": 15.425, "pressure_mb": 1010.0, "precip_mm": 0.0625, "humidity": 81.0}, {"hour": 10, "temp_c": 2.3625000000000003, "wind_kph": 15.2875, "pressure_mb": 1009.875, "precip_mm": 0.075, "humidity": 80.25}, {"hour": 11, "temp_c": 2.0, "wind_kph": 15.200000000000001, "pressure_mb": 1009.75, "precip_mm": 0.45, "humidity": 79.625}, {"hour": 12, "temp_c": 2.125, "wind_kph": 15.25, "pressure_mb": 1009.75, "precip_mm": 0.1, "humidity": 78.75}, {"hour": 13, "temp_c": 2.2375000000000003, "wind_kph": 15.437499999999998, "pressure_mb": 1009.875, "precip_mm": 0.0875, "humidity": 77.875}, {"hour": 14, "temp_c": 2.325, "wind_kph": 15.625, "pressure_mb": 1010.0, "precip_mm": 0.2375, "humidity": 76.5}, {"hour": 15, "temp_c": 2.6500000000000004, "wind_kph": 16.025, "pressure_mb": 1010.0, "precip_mm": 0.0625, "humidity": 75.375}, {"hour": 16, "temp_c": 2.6999999999999997, "wind_kph": 16.2375, "pressure_mb": 1010.0, "precip_mm": 0.05, "humidity": 74.125}, {"hour": 17, "temp_c": 2.8125, "wind_kph": 16.8875, "pressure_mb": 1009.75, "precip_mm": 0.2875, "humidity": 73.125}, {"hour": 18, "temp_c": 2.675, "wind_kph": 17.4, "pressure_mb": 1009.875, "precip_mm": 0.0, "humidity": 73.0}, {"hour": 19, "temp_c": 2.5999999999999996, "wind_kph": 17.95, "pressure_mb": 1010.0, "precip_mm": 0.0, "humidity": 73.25}, {"hour": 20, "temp_c": 3.2500000000000004, "wind_kph": 18.2875, "pressure_mb": 1009.875, "precip_mm": 0.0125, "humidity": 73.875}, {"hour": 21, "temp_c": 3.075, "wind_kph": 17.650000000000002, "pressure_mb": 1010.125, "precip_mm": 0.0, "humidity": 75.25}, {"hour": 22, "temp_c": 2.9499999999999997, "wind_kph": 16.5, "pressure_mb": 1010.125, "precip_mm": 0.0, "humidity": 76.125}, {"hour": 23, "temp_c": 2.6875, "wind_kph": 16.2, "pressure_mb": 1010.125, "precip_mm": 0.025, "humidity": 77.5}]}