{"name": "Donskoy", "region": "Aqmola", "country": "Kazakhstan", "lat": 51.34, "lon": 66.11, "sunrise": 321, "sunset": 1315, "weather": [{"hour": 0, "temp_c": 14.649999999999999, "wind_kph": 14.075000000000001, "pressure_mb": 1008.25, "precip_mm": 0.075, "humidity": 63.5}, {"hour": 1, "temp_c": 14.3125, "wind_kph": 15.712500000000002, "pressure_mb": 1008.25, "precip_mm": 0.025, "humidity": 64.75}, {"hour": 2, "temp_c": 13.837499999999999, "wind_kph": 16.5125, "pressure_mb": 1008.375, "precip_mm": 0.0125, "humidity": 67.0}, {"hour": 3, "temp_c": 13.275000000000002, "wind_kph": 16.75, "pressure_mb": 1008.375, "precip_mm": 0.1375, "humidity": 70.0}, {"hour": 4, "temp_c": 12.775, "wind_kph": 16.6125, "pressure_mb": 1008.375, "precip_mm": 0.05, "humidity": 72.25}, {"hour": 5, "temp_c": 12.550000000000002, "wind_kph": 16.5125, "pressure_mb": 1008.25, "precip_mm": 0.0625, "humidity": 73.5}, {"hour": 6, "temp_c": 12.475, "wind_kph": 16.075, "pressure_mb": 1008.375, "precip_mm": 0.2625, "humidity": 74.5}, {"hour": 7, "temp_c": 13.575, "wind_kph": 15.600000000000001, "pressure_mb": 1008.375, "precip_mm": 0.025, "humidity": 71.75}, {"hour": 8, "temp_c": 15.2375, "wind_kph": 17.237499999999997, "pressure_mb": 1008.25, "precip_mm": 0.0, "humidity": 65.875}, {"hour": 9, "temp_c": 16.7625, "wind_kph": 18.124999999999996, "pressure_mb": 1008.375, "precip_mm": 0.375, "humidity": 60.875}, {"hour": 10, "temp_c": 17.9375, "wind_kph": 18.362499999999997, "pressure_mb": 1008.125, "precip_mm": 0.0, "humidity": 57.75}, {"hour": 11, "temp_c": 19.2375, "wind_kph": 19.612499999999997, "pressure_mb": 1008.125, "precip_mm": 0.125, "humidity": 53.75}, {"hour": 12, "temp_c": 19.7875, "wind_kph": 19.2875, "pressure_mb": 1008.0, "precip_mm": 0.2, "humidity": 51.75}, {"hour": 13, "temp_c": 20.45, "wind_kph": 18.675, "pressure_mb": 1008.0, "precip_mm": 0.21250000000000002, "humidity": 49.875}, {"hour": 14, "temp_c": 20.65, "wind_kph": 18.2625, "pressure_mb": 1007.75, "precip_mm": 0.125, "humidity": 49.875}, {"hour": 15, "temp_c": 20.737499999999997, "wind_kph": 17.412499999999998, "pressure_mb": 1007.75, "precip_mm": 0.5, "humidity": 49.0}, {"hour": 16, "temp_c": 20.650000000000002, "wind_kph": 16.987499999999997, "pressure_mb": 1008.0, "precip_mm": 0.1125, "humidity": 49.0}, {"hour": 17, "temp_c": 21.125, "wind_kph": 16.0125, "pressure_mb": 1007.875, "precip_mm": 0.125, "humidity": 47.25}, {"hour": 18, "temp_c": 21.4625, "wind_kph": 18.2625, "pressure_mb": 1008.0, "precip_mm": 0.4375, "humidity": 46.625}, {"hour": 19, "temp_c": 20.537500000000005, "wind_kph": 17.775, "pressure_mb": 1008.125, "precip_mm": 0.075, "humidity": 51.0}, {"hour": 20, "temp_c": 19.8, "wind_kph": 17.1125, "pressure_mb": 1008.375, "precip_mm": 0.0, "humidity": 54.25}, {"hour": 21, "temp_c": 18.3125, "wind_kph": 15.749999999999998, "pressure_mb": 1008.5, "precip_mm": 0.11249999999999999, "humidity": 59.75}, {"hour": 22, "temp_c": 17.037499999999998, "wind_kph": 16.625, "pressure_mb": 1008.75, "precip_mm": 0.0, "humidity": 62.625}, {"hour": 23, "temp_c": 16.35, "wind_kph": 16.7875, "pressure_mb": 1009.0, "precip_mm": 0.025, "humidity": 64.25}]}