{"name": "Blaukehl", "region": "Karas", "country": "Namibia", "lat": -26.15, "lon": 18.3, "sunrise": 454, "sunset": 1085, "weather": [{"hour": 0, "temp_c": 11.950000000000001, "wind_kph": 12.925, "pressure_mb": 1019.625, "precip_mm": 0.0, "humidity": 47.0}, {"hour": 1, "temp_c": 11.25, "wind_kph": 11.6125, "pressure_mb": 1019.5, "precip_mm": 0.0, "humidity": 50.125}, {"hour": 2, "temp_c": 10.8125, "wind_kph": 10.849999999999998, "pressure_mb": 1019.5, "precip_mm": 0.0, "humidity": 52.125}, {"hour": 3, "temp_c": 10.625, "wind_kph": 10.575000000000001, "pressure_mb": 1019.375, "precip_mm": 0.0, "humidity": 51.5}, {"hour": 4, "temp_c": 10.2625, "wind_kph": 11.025, "pressure_mb": 1019.25, "precip_mm": 0.0, "humidity": 51.875}, {"hour": 5, "temp_c": 9.9125, "wind_kph": 11.475000000000001, "pressure_mb": 1019.5, "precip_mm": 0.0, "humidity": 51.875}, {"hour": 6, "temp_c": 9.575, "wind_kph": 11.299999999999999, "pressure_mb": 1020.0, "precip_mm": 0.0, "humidity": 52.125}, {"hour": 7, "temp_c": 9.825000000000001, "wind_kph": 11.512500000000001, "pressure_mb": 1020.625, "precip_mm": 0.0, "humidity": 51.0}, {"hour": 8, "temp_c": 12.075, "wind_kph": 13.3625, "pressure_mb": 1020.75, "precip_mm": 0.0, "humidity": 43.5}, {"hour": 9, "temp_c": 14.325000000000001, "wind_kph": 15.975, "pressure_mb": 1020.625, "precip_mm": 0.0, "humidity": 38.625}, {"hour": 10, "temp_c": 16.125, "wind_kph": 17.175, "pressure_mb": 1020.25, "precip_mm": 0.0, "humidity": 35.0}, {"hour": 11, "temp_c": 18.225, "wind_kph": 18.3875, "pressure_mb": 1019.375, "precip_mm": 0.0, "humidity": 31.875}, {"hour": 12, "temp_c": 19.325, "wind_kph": 18.5, "pressure_mb": 1018.25, "precip_mm": 0.0, "humidity": 30.125}, {"hour": 13, "temp_c": 20.3875, "wind_kph": 19.0875, "pressure_mb": 1016.875, "precip_mm": 0.0125, "humidity": 28.25}, {"hour": 14, "temp_c": 20.900000000000002, "wind_kph": 19.275000000000002, "pressure_mb": 1016.125, "precip_mm": 0.0, "humidity": 26.5}, {"hour": 15, "temp_c": 21.075, "wind_kph": 20.462500000000002, "pressure_mb": 1015.875, "precip_mm": 0.0, "humidity": 25.875}, {"hour": 16, "temp_c": 20.662499999999998, "wind_kph": 19.375, "pressure_mb": 1015.75, "precip_mm": 0.0, "humidity": 26.75}, {"hour": 17, "temp_c": 18.837500000000002, "wind_kph": 18.487500000000004, "pressure_mb": 1016.25, "precip_mm": 0.0, "humidity": 30.375}, {"hour": 18, "temp_c": 17.4125, "wind_kph": 18.575000000000003, "pressure_mb": 1017.25, "precip_mm": 0.0, "humidity": 33.5}, {"hour": 19, "temp_c": 16.3875, "wind_kph": 17.9, "pressure_mb": 1018.25, "precip_mm": 0.0, "humidity": 36.25}, {"hour": 20, "temp_c": 14.15, "wind_kph": 16.825, "pressure_mb": 1019.0, "precip_mm": 0.0, "humidity": 40.25}, {"hour": 21, "temp_c": 13.5, "wind_kph": 15.787499999999998, "pressure_mb": 1019.5, "precip_mm": 0.0, "humidity": 42.125}, {"hour": 22, "temp_c": 12.975000000000001, "wind_kph": 15.524999999999999, "pressure_mb": 1019.75, "precip_mm": 0.0, "humidity": 43.875}, {"hour": 23, "temp_c": 12.2625, "wind_kph": 14.6875, "pressure_mb": 1020.0, "precip_mm": 0.0, "humidity": 46.375}]}