{"name": "Douna", "region": "Niamey", "country": "Niger", "lat": 14.65, "lon": 4.16, "sunrise": 376, "sunset": 1156, "weather": [{"hour": 0, "temp_c": 30.249999999999996, "wind_kph": 19.487499999999997, "pressure_mb": 1011.0, "precip_mm": 0.4375, "humidity": 49.875}, {"hour": 1, "temp_c": 29.887500000000003, "wind_kph": 18.675, "pressure_mb": 1010.125, "precip_mm": 2.5875000000000004, "humidity": 50.375}, {"hour": 2, "temp_c": 29.3875, "wind_kph": 19.3625, "pressure_mb": 1010.125, "precip_mm": 0.2625, "humidity": 51.375}, {"hour": 3, "temp_c": 28.974999999999998, "wind_kph": 17.950000000000003, "pressure_mb": 1010.0, "precip_mm": 0.3125, "humidity": 52.75}, {"hour": 4, "temp_c": 28.462499999999995, "wind_kph": 20.750000000000004, "pressure_mb": 1010.375, "precip_mm": 0.7999999999999999, "humidity": 53.5}, {"hour": 5, "temp_c": 28.0375, "wind_kph": 21.825, "pressure_mb": 1010.5, "precip_mm": 0.19999999999999998, "humidity": 54.875}, {"hour": 6, "temp_c": 27.875, "wind_kph": 19.85, "pressure_mb": 1011.0, "precip_mm": 0.175, "humidity": 55.625}, {"hour": 7, "temp_c": 28.0, "wind_kph": 18.8625, "pressure_mb": 1011.875, "precip_mm": 0.825, "humidity": 56.125}, {"hour": 8, "temp_c": 28.650000000000002, "wind_kph": 22.275, "pressure_mb": 1012.125, "precip_mm": 0.0, "humidity": 54.75}, {"hour": 9, "temp_c": 29.637500000000003, "wind_kph": 23.400000000000002, "pressure_mb": 1012.625, "precip_mm": 0.0, "humidity": 52.625}, {"hour": 10, "temp_c": 30.8125, "wind_kph": 23.9375, "pressure_mb": 1012.5, "precip_mm": 0.0125, "humidity": 48.875}, {"hour": 11, "temp_c": 34.162499999999994, "wind_kph": 24.2125, "pressure_mb": 1012.25, "precip_mm": 0.0, "humidity": 44.875}, {"hour": 12, "temp_c": 35.199999999999996, "wind_kph": 24.4875, "pressure_mb": 1011.75, "precip_mm": 0.0, "humidity": 41.5}, {"hour": 13, "temp_c": 35.525, "wind_kph": 23.25, "pressure_mb": 1010.75, "precip_mm": 0.0125, "humidity": 39.125}, {"hour": 14, "temp_c": 36.525, "wind_kph": 21.475, "pressure_mb": 1010.0, "precip_mm": 0.0, "humidity": 36.625}, {"hour": 15, "temp_c": 36.7625, "wind_kph": 19.725, "pressure_mb": 1009.125, "precip_mm": 0.0, "humidity": 34.75}, {"hour": 16, "temp_c": 36.74999999999999, "wind_kph": 18.05, "pressure_mb": 1008.5, "precip_mm": 0.0, "humidity": 33.625}, {"hour": 17, "temp_c": 36.5125, "wind_kph": 15.6625, "pressure_mb": 1008.25, "precip_mm": 0.0, "humidity": 32.625}, {"hour": 18, "temp_c": 36.0625, "wind_kph": 15.350000000000001, "pressure_mb": 1008.375, "precip_mm": 0.0, "humidity": 32.875}, {"hour": 19, "temp_c": 34.45, "wind_kph": 15.7, "pressure_mb": 1008.5, "precip_mm": 0.1125, "humidity": 36.75}, {"hour": 20, "temp_c": 32.5, "wind_kph": 15.7125, "pressure_mb": 1009.125, "precip_mm": 0.6625, "humidity": 42.75}, {"hour": 21, "temp_c": 32.025, "wind_kph": 14.5375, "pressure_mb": 1009.625, "precip_mm": 0.6125, "humidity": 42.875}, {"hour": 22, "temp_c": 32.1625, "wind_kph": 14.312499999999998, "pressure_mb": 1010.125, "precip_mm": 1.3, "humidity": 42.625}, {"hour": 23, "temp_c": 31.9625, "wind_kph": 15.162500000000001, "pressure_mb": 1010.125, "precip_mm": 0.3125, "humidity": 43.125}]}