{"name": "Spar City", "region": "Colorado", "country": "United States of America", "lat": 37.56, "lon": -107.04, "sunrise": 349, "sunset": 1233, "weather": [{"hour": 0, "temp_c": 15.0875, "wind_kph": 7.675, "pressure_mb": 1015.625, "precip_mm": 0.0, "humidity": 23.375}, {"hour": 1, "temp_c": 10.875, "wind_kph": 7.512499999999999, "pressure_mb": 1017.875, "precip_mm": 0.0, "humidity": 32.375}, {"hour": 2, "temp_c": 10.000000000000002, "wind_kph": 7.6875, "pressure_mb": 1018.5, "precip_mm": 0.0, "humidity": 34.125}, {"hour": 3, "temp_c": 12.475, "wind_kph": 7.4625, "pressure_mb": 1016.75, "precip_mm": 0.0, "humidity": 30.25}, {"hour": 4, "temp_c": 9.450000000000001, "wind_kph": 7.437499999999999, "pressure_mb": 1019.0, "precip_mm": 0.0, "humidity": 37.25}, {"hour": 5, "temp_c": 9.025, "wind_kph": 7.562499999999999, "pressure_mb": 1019.125, "precip_mm": 0.0125, "humidity": 39.75}, {"hour": 6, "temp_c": 10.85, "wind_kph": 7.475, "pressure_mb": 1018.125, "precip_mm": 0.0, "humidity": 30.625}, {"hour": 7, "temp_c": 11.399999999999999, "wind_kph": 5.7124999999999995, "pressure_mb": 1019.125, "precip_mm": 0.05, "humidity": 40.75}, {"hour": 8, "temp_c": 16.05, "wind_kph": 2.8874999999999997, "pressure_mb": 1017.625, "precip_mm": 0.0, "humidity": 32.375}, {"hour": 9, "temp_c": 17.9125, "wind_kph": 5.2625, "pressure_mb": 1016.5, "precip_mm": 0.0, "humidity": 29.625}, {"hour": 10, "temp_c": 21.412499999999998, "wind_kph": 9.45, "pressure_mb": 1015.0, "precip_mm": 0.0, "humidity": 20.5}, {"hour": 11, "temp_c": 23.187500000000004, "wind_kph": 13.674999999999999, "pressure_mb": 1014.0, "precip_mm": 0.0125, "humidity": 16.625}, {"hour": 12, "temp_c": 21.375, "wind_kph": 17.85, "pressure_mb": 1015.375, "precip_mm": 0.0, "humidity": 23.375}, {"hour": 13, "temp_c": 24.300000000000004, "wind_kph": 20.3, "pressure_mb": 1012.25, "precip_mm": 0.0, "humidity": 13.5}, {"hour": 14, "temp_c": 24.962500000000006, "wind_kph": 22.225, "pressure_mb": 1011.0, "precip_mm": 0.0, "humidity": 12.125}, {"hour": 15, "temp_c": 23.349999999999998, "wind_kph": 22.725, "pressure_mb": 1013.625, "precip_mm": 0.0, "humidity": 19.625}, {"hour": 16, "temp_c": 24.8875, "wind_kph": 20.762500000000003, "pressure_mb": 1009.625, "precip_mm": 0.0, "humidity": 12.375}, {"hour": 17, "temp_c": 24.462499999999995, "wind_kph": 22.175, "pressure_mb": 1009.25, "precip_mm": 0.0, "humidity": 12.625}, {"hour": 18, "temp_c": 22.925, "wind_kph": 20.2625, "pressure_mb": 1012.375, "precip_mm": 0.0, "humidity": 19.625}, {"hour": 19, "temp_c": 21.974999999999998, "wind_kph": 16.837500000000002, "pressure_mb": 1010.125, "precip_mm": 0.0125, "humidity": 18.125}, {"hour": 20, "temp_c": 17.325, "wind_kph": 9.3375, "pressure_mb": 1012.25, "precip_mm": 0.0, "humidity": 26.875}, {"hour": 21, "temp_c": 19.250000000000004, "wind_kph": 8.1375, "pressure_mb": 1013.875, "precip_mm": 0.0, "humidity": 25.875}, {"hour": 22, "temp_c": 12.075000000000001, "wind_kph": 7.575, "pressure_mb": 1016.0, "precip_mm": 0.0, "humidity": 32.5}, {"hour": 23, "temp_c": 12.2875, "wind_kph": 8.1, "pressure_mb": 1016.75, "precip_mm": 0.0, "humidity": 34.25}]}