{"name": "Atqasuk", "region": "Alaska", "country": "United States of America", "lat": 70.37, "lon": -156.4, "sunrise": 720, "sunset": 720, "weather": [{"hour": 0, "temp_c": 3.75, "wind_kph": 14.500000000000002, "pressure_mb": 1008.875, "precip_mm": 0.0125, "humidity": 84.75}, {"hour": 1, "temp_c": 3.5375, "wind_kph": 13.950000000000001, "pressure_mb": 1009.0, "precip_mm": 0.05, "humidity": 85.625}, {"hour": 2, "temp_c": 3.4125, "wind_kph": 13.675, "pressure_mb": 1008.875, "precip_mm": 0.0125, "humidity": 86.25}, {"hour": 3, "temp_c": 3.25, "wind_kph": 13.7625, "pressure_mb": 1008.875, "precip_mm": 0.0125, "humidity": 86.875}, {"hour": 4, "temp_c": 2.8749999999999996, "wind_kph": 14.049999999999997, "pressure_mb": 1009.125, "precip_mm": 0.05, "humidity": 87.5}, {"hour": 5, "temp_c": 2.8625000000000003, "wind_kph": 14.312499999999998, "pressure_mb": 1009.0, "precip_mm": 0.0125, "humidity": 86.625}, {"hour": 6, "temp_c": 3.0125, "wind_kph": 14.587499999999999, "pressure_mb": 1009.25, "precip_mm": 0.0125, "humidity": 86.0}, {"hour": 7, "temp_c": 3.2375000000000007, "wind_kph": 13.9375, "pressure_mb": 1009.25, "precip_mm": 0.025, "humidity": 84.625}, {"hour": 8, "temp_c": 3.575, "wind_kph": 13.8125, "pressure_mb": 1009.375, "precip_mm": 0.0, "humidity": 83.0}, {"hour": 9, "temp_c": 3.9250000000000003, "wind_kph": 13.725, "pressure_mb": 1009.25, "precip_mm": 0.0125, "humidity": 81.75}, {"hour": 10, "temp_c": 4.3625, "wind_kph": 13.975000000000001, "pressure_mb": 1009.375, "precip_mm": 0.11249999999999999, "humidity": 79.875}, {"hour": 11, "temp_c": 5.012499999999999, "wind_kph": 12.912499999999998, "pressure_mb": 1009.5, "precip_mm": 0.0625, "humidity": 77.75}, {"hour": 12, "temp_c": 5.875000000000001, "wind_kph": 12.675, "pressure_mb": 1009.375, "precip_mm": 0.15000000000000002, "humidity": 75.375}, {"hour": 13, "temp_c": 6.45, "wind_kph": 12.587499999999999, "pressure_mb": 1009.625, "precip_mm": 0.475, "humidity": 74.5}, {"hour": 14, "temp_c": 6.4875, "wind_kph": 12.75, "pressure_mb": 1009.5, "precip_mm": 0.1375, "humidity": 74.0}, {"hour": 15, "temp_c": 6.062500000000001, "wind_kph": 12.774999999999999, "pressure_mb": 1009.75, "precip_mm": 0.1125, "humidity": 74.875}, {"hour": 16, "temp_c": 6.0375, "wind_kph": 13.025000000000002, "pressure_mb": 1009.625, "precip_mm": 0.6000000000000001, "humidity": 75.125}, {"hour": 17, "temp_c": 5.887499999999999, "wind_kph": 12.862499999999999, "pressure_mb": 1009.625, "precip_mm": 0.0125, "humidity": 76.125}, {"hour": 18, "temp_c": 5.7625, "wind_kph": 12.549999999999999, "pressure_mb": 1009.875, "precip_mm": 0.0, "humidity": 76.625}, {"hour": 19, "temp_c": 5.575000000000001, "wind_kph": 13.0625, "pressure_mb": 1009.75, "precip_mm": 0.0125, "humidity": 77.0}, {"hour": 20, "temp_c": 5.1000000000000005, "wind_kph": 13.0, "pressure_mb": 1009.875, "precip_mm": 0.0, "humidity": 78.125}, {"hour": 21, "temp_c": 4.699999999999999, "wind_kph": 12.3, "pressure_mb": 1009.875, "precip_mm": 0.0, "humidity": 79.75}, {"hour": 22, "temp_c": 4.4875, "wind_kph": 12.7875, "pressure_mb": 1010.0, "precip_mm": 0.025, "humidity": 80.625}, {"hour": 23, "temp_c": 4.312499999999999, "wind_kph": 12.55, "pressure_mb": 1010.125, "precip_mm": 0.0125, "humidity": 81.25}]}